velovgi/__init__.py
VeloVGI-0.1.0.dist-info/LICENSE
VeloVGI-0.1.0.dist-info/METADATA
VeloVGI-0.1.0.dist-info/WHEEL
VeloVGI-0.1.0.dist-info/top_level.txt
VeloVGI-0.1.0.dist-info/RECORD
